humanencoding/__init__.py
humanencoding/encoder.py
humanencoding/wordlist_v1.py
tests/__init__.py
tests/test_encoder.py
humanencoding-0.2.dist-info/LICENSE
humanencoding-0.2.dist-info/METADATA
humanencoding-0.2.dist-info/WHEEL
humanencoding-0.2.dist-info/top_level.txt
humanencoding-0.2.dist-info/RECORD
